[
    {
        "id": "1349A807-87CA-446C-9740-480238489517",
        "title": "Book title1",
        "genres": [
            "detective",
            "comedy"
        ],
        "pages": 321,
        "price": 12.43
    },
    {
        "id": "C97376B9-6C2E-41E5-9DBE-2E82C0EF114B",
        "title": "Book title2",
        "genres": [
            "adventure"
        ],
        "pages": 234,
        "price": 25.43
    },
    {
        "id": "FFAD23EB-8FF4-4E09-82D2-AA33EBE3997F",
        "title": "Book title3",
        "genres": [
            "historical"
        ],
        "pages": 321,
        "price": 999
    }
]
